LICENSE
README.md
setup.py
orchest_cli.egg-info/PKG-INFO
orchest_cli.egg-info/SOURCES.txt
orchest_cli.egg-info/dependency_links.txt
orchest_cli.egg-info/entry_points.txt
orchest_cli.egg-info/requires.txt
orchest_cli.egg-info/top_level.txt
orchestcli/__init__.py
orchestcli/_version.py
orchestcli/cli.py
orchestcli/cmds.py
orchestcli/utils.py